Workbook
Name Satis: '1. Girdiler'!$C$6
Name SatisKDV: '1. Girdiler'!$C$7
Name Alis: '1. Girdiler'!$C$8
Name AlisKDV: '1. Girdiler'!$C$9
Name KDVsizGider: '1. Girdiler'!$C$10
Name KKEG: '1. Girdiler'!$C$11
Name KiraAylik: '1. Girdiler'!$C$14
Name KiraStopaj: '1. Girdiler'!$C$15
Name Calisan: '1. Girdiler'!$C$18
Name BrutMaas: '1. Girdiler'!$C$19
Name SGKisci: '1. Girdiler'!$C$20
Name IssizlikIsci: '1. Girdiler'!$C$21
Name SGKisveren: '1. Girdiler'!$C$22
Name IssizlikIsveren: '1. Girdiler'!$C$23
Name Damga: '1. Girdiler'!$C$24
Name AsgariUcret: '1. Girdiler'!$C$25
Name KVoran: '1. Girdiler'!$C$28
Name GeciciVergi: '1. Girdiler'!$C$29
Name TemettuVarMi: '1. Girdiler'!$C$30
Name TemettuStopaj: '1. Girdiler'!$C$31
Name AsgariKVoran: '1. Girdiler'!$C$34
Name YeniSirket: '1. Girdiler'!$C$35

Sheet 1. Girdiler
B1: TÜRKİYE LİMİTED ŞİRKETİ – 2026 VERGİ HESAPLAMA TABLOSU
B2: Sarı hücreler = girdi (düzenleyebilirsiniz). Yeşil hücreler = otomatik hesaplanır.
B4: 1.A Yıllık Gelir, Maliyet ve KDV Oranları
B5: Parametre | C5: Değer | D5: Birim | E5: Açıklama
B6: Yıllık satış / hasılat (KDV HARİÇ) | C6: 1000000 | D6: ₺ | E6: Kullanıcı varsayımı: 1.000.000 ₺ fatura kesimi (KDV hariç tutar).
B7: Satış KDV oranı | C7: 0.2 | D7: % | E7: Standart oran 2026 itibarıyla %20. Gıda %10, kitap %1 olabilir.
B8: Yıllık alış / gider (KDV HARİÇ, indirilebilir) | C8: 350000 | D8: ₺ | E8: Mal/hizmet alımı, kira, fatura vb. KDV'si indirilebilen giderler.
B9: Alış KDV oranı (ortalama) | C9: 0.2 | D9: % | E9: Alımların ağırlıklı ortalama KDV oranı.
B10: KDV'siz / belgesiz giderler (yıllık) | C10: 0 | D10: ₺ | E10: KKEG dışı ama KDV içermeyen giderler (örn. SGK primleri zaten ayrı).
B11: Kanunen kabul edilmeyen giderler (KKEG) | C11: 0 | D11: ₺ | E11: Cezalar, özel binek araç giderlerinin bir kısmı vb. → Kurumlar Vergisi matrahına eklenir.
B13: 1.B İşyeri Kirası ve Stopaj
B14: Aylık brüt işyeri kirası (gerçek kişiden) | C14: 0 | D14: ₺/ay | E14: Gerçek kişi mal sahibinden kiralanıyorsa kiracı stopaj keser.
B15: İşyeri kira stopaj oranı (GVK 94/5) | C15: 0.2 | D15: % | E15: 2026 itibarıyla %20 (geçici düzenleme sona ererse).
B17: 1.C Çalışan / Personel Maliyeti
B18: Çalışan sayısı | C18: 0 | D18: kişi | E18: 0 girilirse personel maliyeti hesaplanmaz. Çalışan yoksa SGK primi yoktur.
B19: Ortalama aylık BRÜT maaş (kişi başı) | C19: 30000 | D19: ₺/ay | E19: Brüt maaş üzerinden tüm kesintiler ve işveren maliyeti hesaplanır.
B20: SGK işçi payı | C20: 0.14 | D20: % | E20: Standart %14 (5510 SK).
B21: İşsizlik sigortası işçi payı | C21: 0.01 | D21: %
B22: SGK işveren payı (5 puan indirim DAHİL %15,5) | C22: 0.155 | D22: % | E22: Normalde %20,5; 5510/Ek-81 indiriminden yararlanan işverenler %15,5 öder.
B23: İşsizlik sigortası işveren payı | C23: 0.02 | D23: %
B24: Damga vergisi oranı (ücret) | C24: 0.00759 | D24: % | E24: Binde 7,59 (488 SK).
B25: Aylık asgari ücret (brüt) – 2026 varsayımı | C25: 30000 | D25: ₺/ay | E25: Asgari ücretten gelir/damga istisnası için kullanılır. 2026 rakamı netleştiğinde güncelleyin.
B27: 1.D Kurumlar Vergisi ve Kâr Dağıtımı
B28: Kurumlar vergisi oranı | C28: 0.25 | D28: % | E28: 2026 için genel oran %25. Bankalar/finans %30; halka açık (BIST %20+ fiili dolaşım) %23.
B29: Geçici (peşin) vergi oranı | C29: 0.25 | D29: % | E29: 3 aylık dönemler hâlinde ödenir, yıl sonunda kurumlar vergisinden mahsup edilir.
B30: Kâr dağıtımı yapılacak mı? | C30: EVET | E30: EVET / HAYIR. EVET ise kalan net kâr üzerinden temettü stopajı hesaplanır.
B31: Temettü (kâr payı) stopaj oranı | C31: 0.15 | D31: % | E31: 2025 sonu itibarıyla %15 (önceden %10 idi).
B33: 1.E Diğer / Muafiyetler
B34: Asgari kurumlar vergisi oranı (yurt içi) | C34: 0.1 | D34: % | E34: 7524 SK ile getirilen yurt içi asgari kurumlar vergisi (indirim öncesi matraha %10).
B35: Yeni kurulan şirket istisnası (ilk 3 yıl)? | C35: HAYIR | E35: Asgari kurumlar vergisi yeni kurulanlar için ilk 3 yıl uygulanmaz (EVET = muaf).

Sheet 2. KDV
B1: KDV (KATMA DEĞER VERGİSİ) HESABI – YILLIK
B2: KDV her ay beyan edilir. Burada yıllık toplam gösterilmiştir.
B4: Hesaplanan KDV (Satışlardan)
B5: Satış tutarı (KDV hariç) | C5: =Satis | D5: Girdiler sayfasından
B6: Satış KDV oranı | C6: =SatisKDV
B7: Hesaplanan KDV (output VAT) | C7: =Satis*SatisKDV | D7: Müşteriden tahsil edilen KDV
B9: İndirilecek KDV (Alışlardan)
B10: Alış tutarı (KDV hariç) | C10: =Alis
B11: Alış KDV oranı | C11: =AlisKDV
B12: İndirilecek KDV (input VAT) | C12: =Alis*AlisKDV | D12: Tedarikçilere ödenen ve mahsup edilen KDV
B14: Ödenecek KDV
B15: Net Ödenecek KDV (yıllık) | C15: =MAX(0, C7-C12) | D15: =Hesaplanan KDV - İndirilecek KDV. Negatifse devrolur, ödenmez.
B16: Devreden KDV (varsa) | C16: =MAX(0, C12-C7) | D16: İndirilecek KDV > Hesaplanan KDV ise sonraki aya devreder.
B17: Aylık ortalama ödenecek KDV | C17: =C15/12
B19: ÖNEMLİ NOTLAR:
B20: • KDV beyannamesi her ayın 28'ine kadar verilir, ödeme aynı tarihtir.
B21: • 2026 standart KDV oranı %20'dir. İndirimli oranlar: gıda %10, kitap-eğitim %1, sağlık %10.
B22: • Limited Şirket KDV mükellefidir; muafiyet yoktur (basit usul gerçek kişiler içindir).
B23: • Tevkifatlı KDV (örn. yapım, danışmanlık) ayrıca dikkate alınmalıdır.

Sheet 3. Çalışan Maliyeti
B1: ÇALIŞAN MALİYETİ – AYLIK VE YILLIK
B2: Çalışan sayısı 0 ise tüm sonuçlar 0 olur. Gelir vergisi 2026 dilimleri ile hesaplanır.
C4: KİŞİ BAŞI / AY | D4: TOPLAM / YIL
B5: A) İşçi Brüt Maaş ve Kesintiler
B6: Brüt maaş | C6: =BrutMaas | D6: =C6*Calisan*12
B7: (-) SGK işçi payı (%14) | C7: =C6*SGKisci | D7: =C7*Calisan*12
B8: (-) İşsizlik işçi payı (%1) | C8: =C6*IssizlikIsci | D8: =C8*Calisan*12
B9: Gelir vergisi matrahı (aylık) | C9: =C6-C7-C8 | D9: =C9*Calisan*12
B10: (-) Gelir vergisi (yıllık kümülatif matraha göre) | C10: =IF(C9*12<=200000, C9*12*0.15, IF(C9*12<=420000, 30000+(C9*12-200000)*0.20, IF(C9*12<=1500000, 74000+(C9*12-420000)*0.27, IF(C9*12<=5500000, 365600+(C9*12-1500000)*0.35, 1765600+(C9*12-5500000)*0.40))))/12 | D10: =C10*Calisan*12 | E10: 2026 dilim tahminleri: 200k/420k/1.5M/5.5M ₺ (resmî dilimler açıklandığında güncelleyin).
B11: (-) Damga vergisi (binde 7,59) | C11: =C6*Damga | D11: =C11*Calisan*12
B12: (+) Asgari ücret istisnası (GV+DV) | C12: =IF(Calisan=0,0, ((AsgariUcret-AsgariUcret*(SGKisci+IssizlikIsci))*0.15 + AsgariUcret*Damga)) | D12: =C12*Calisan*12 | E12: Asgari ücret üzerinden hesaplanan GV+DV istisna; net maaşa eklenir.
B13: NET MAAŞ (çalışana ödenen) | C13: =C6-C7-C8-C10-C11+C12 | D13: =C13*Calisan*12
B15: B) İşveren Maliyetleri (Brüt Üzerinden)
B16: SGK işveren payı (%15,5 indirimli / %20,5 normal) | C16: =C6*SGKisveren | D16: =C16*Calisan*12
B17: İşsizlik işveren payı (%2) | C17: =C6*IssizlikIsveren | D17: =C17*Calisan*12
B18: TOPLAM İŞVEREN MALİYETİ (kişi başı/ay – yıllık) | C18: =C6+C16+C17 | D18: =C18*Calisan*12 | E18: Şirket için tek bir çalışanın gerçek yıllık maliyeti.
B20: C) Muhtasar Beyanname ile Ödenecekler (Yıllık)
B21: Çalışan gelir vergisi stopajı (yıllık, istisna sonrası) | C21: =MAX(0, (D10+D11) - D12) | E21: Muhtasar beyanname ile her ay/3 ayda bir ödenir.
B22: Kira stopajı (gerçek kişiden kira ödeniyorsa) | C22: =KiraAylik*12*KiraStopaj | E22: Aylık brüt kira × 12 × %20.
B23: TOPLAM MUHTASAR | C23: =C21+C22
B25: MUAFİYET/AVANTAJ NOTLARI:
B26: • Çalışan yoksa (Çalışan=0): SGK ve gelir vergisi stopajı yok, ancak ortaklar BAĞ-KUR (4/b) ödemekle yükümlüdür.
B27: • Asgari ücretten hesaplanan gelir vergisi + damga vergisi istisnadır (tüm çalışanlar için).
B28: • İlk defa işe alınan kadın/genç/engelli için ek SGK teşvikleri (4447 SK 19, 7103 SK) olabilir.
B29: • 10'dan az çalışanı olanlar muhtasarı 3 ayda bir verebilir; aksi hâlde aylık.

Sheet 4. Kurumlar Vergisi
B1: KURUMLAR VERGİSİ HESABI – YILLIK
B2: Ticari kâr → KKEG/istisnalarla mali kâra çevrilir → vergi hesaplanır.
B4: A) Ticari Kâr Hesabı (Kazanç)
B5: Satış geliri (KDV hariç) | C5: =Satis
B6: (-) Mal/hizmet alımları & giderler (KDV hariç) | C6: =Alis
B7: (-) KDV'siz/belgesiz indirilebilir giderler | C7: =KDVsizGider
B8: (-) Yıllık kira gideri (brüt) | C8: =KiraAylik*12 | D8: Brüt kira gider, stopaj ayrıca düşülmez; sadece muhasebede gider.
B9: (-) Toplam personel gideri (işveren maliyeti) | C9: ='3. Çalışan Maliyeti'!D18
B10: TİCARİ KÂR | C10: =C5-C6-C7-C8-C9
B12: B) Mali Kâr (Vergi Matrahı)
B13: Ticari kâr | C13: =C10
B14: (+) Kanunen kabul edilmeyen giderler (KKEG) | C14: =KKEG
B15: (-) İstisna ve indirimler | C15: 0 | D15: Manuel: AR-GE indirimi, iştirak kazancı istisnası, KOBİ birleşme istisnası vb.
B16: VERGİ MATRAHI (Mali Kâr) | C16: =MAX(0, C10+C14-C15)
B18: C) Kurumlar Vergisi
B19: Hesaplanan kurumlar vergisi (matrah × %25) | C19: =C16*KVoran
B20: Yurt içi asgari kurumlar vergisi (matrah × %10) | C20: =IF(UPPER(TRIM(YeniSirket))="EVET",0, C16*AsgariKVoran) | D20: 7524 SK. Yeni kurulan şirketler ilk 3 yıl muaf. Hesaplanan KV bundan azsa fark ödenir.
B21: ÖDENECEK KURUMLAR VERGİSİ (en büyük olanı) | C21: =MAX(C19, C20)
B22: Geçici (peşin) vergi (3 ayda bir, yıl içinde ödenen) | C22: =C21 | D22: 3 aylık dönemlerde ödenir, yıl sonunda mahsup edilir; ek bir vergi DEĞİL.
B24: D) Net Kâr ve Temettü
B25: VERGİ SONRASI NET KÂR (ortaklara dağıtılabilir) | C25: =C10-C21
B26: Temettü stopajı (kâr dağıtımı yapılırsa) | C26: =IF(UPPER(TRIM(TemettuVarMi))="EVET", MAX(0,C25)*TemettuStopaj, 0) | D26: Net kâr ortaklara dağıtılırsa şirket %15 stopaj keser ve muhtasar ile öder.
B27: ORTAKLARIN ELİNE GEÇEN NET TEMETTÜ | C27: =IF(UPPER(TRIM(TemettuVarMi))="EVET", MAX(0,C25)-C26, 0)
B28: Not: Gerçek kişi ortak temettüyü beyan eder; %15 stopaj mahsup edilir, dilime göre ek vergi çıkabilir.

Sheet 5. Stopajlar
B1: STOPAJ (KAYNAĞINDA KESİLEN VERGİ) ÖZETİ – YILLIK
B3: Muhtasar Beyanname Kalemleri
B4: Ücret stopajı (çalışanlardan) | C4: ='3. Çalışan Maliyeti'!C21
B5: Kira stopajı (işyeri kirası) | C5: ='3. Çalışan Maliyeti'!C22 | D5: Aylık brüt kira × 12 × %20
B6: Serbest meslek stopajı (varsa) | C6: 0 | D6: SMM, avukat, mali müşavir gibi serbest meslek erbabına yapılan ödemelerde %20.
B7: Temettü stopajı (kâr dağıtımı) | C7: ='4. Kurumlar Vergisi'!C26
B8: TOPLAM MUHTASAR / YIL | C8: =SUM(C4:C7)
B10: Muhtasar beyanname genelde takip eden ayın 26'sına kadar verilir, 26'sına kadar ödenir.

Sheet 6. ÖZET
B1: ŞİRKETİN YILLIK TOPLAM VERGİ YÜKÜ – ÖZET TABLO
B2: Aşağıdaki tüm rakamlar Girdiler sayfasındaki varsayımlardan otomatik hesaplanır.
B4: Vergi / Kalem | C4: Yıllık Tutar | D4: Hasılat % | E4: Beyan / Ödeme Dönemi
B5: Ödenecek KDV (yıllık net) | C5: ='2. KDV'!C15 | D5: =C5/Satis | E5: Aylık, 28'i
B6: Kurumlar vergisi | C6: ='4. Kurumlar Vergisi'!C21 | D6: =C6/Satis | E6: Yıllık (Nisan); geçici 3 ayda bir
B7: Ücret stopajı (muhtasar) | C7: ='5. Stopajlar'!C4 | D7: =C7/Satis | E7: Aylık/3 aylık, 26'sı
B8: Kira stopajı (muhtasar) | C8: ='5. Stopajlar'!C5 | D8: =C8/Satis | E8: Aylık/3 aylık, 26'sı
B9: Serbest meslek stopajı | C9: ='5. Stopajlar'!C6 | D9: =C9/Satis | E9: Aylık/3 aylık, 26'sı
B10: Temettü stopajı | C10: ='5. Stopajlar'!C7 | D10: =C10/Satis | E10: Dağıtım yapıldığında
B11: SGK işveren primi (yıllık) | C11: ='3. Çalışan Maliyeti'!D16 | D11: =C11/Satis | E11: Aylık, takip eden ayın sonu
B12: İşsizlik işveren primi (yıllık) | C12: ='3. Çalışan Maliyeti'!D17 | D12: =C12/Satis | E12: Aylık, takip eden ayın sonu
B13: ŞİRKETİN ÖDEDİĞİ TOPLAM (vergi + SGK) | C13: =SUM(C5:C12) | D13: =C13/Satis
B15: Hızlı Panel
B16: Yıllık satış (KDV hariç) | C16: =Satis
B17: Yıllık alış (KDV hariç) | C17: =Alis
B18: Ticari kâr (vergi öncesi) | C18: ='4. Kurumlar Vergisi'!C10
B19: Vergi matrahı (mali kâr) | C19: ='4. Kurumlar Vergisi'!C16
B20: Vergi sonrası net kâr | C20: ='4. Kurumlar Vergisi'!C25
B21: Ortakların eline geçen (temettü sonrası) | C21: ='4. Kurumlar Vergisi'!C27
B22: Toplam personel maliyeti (işveren) | C22: ='3. Çalışan Maliyeti'!D18
B23: Çalışan sayısı | C23: =Calisan
B25: → İlk sayfadaki sarı hücreleri değiştirerek tüm tabloyu kendi senaryonuza uyarlayabilirsiniz.

Sheet 7. Notlar & Oranlar
B1: 2026 VERGİ ORANLARI VE ÖNEMLİ NOTLAR
B3: KDV oranları | C3: Standart %20 | İndirimli %10 (gıda, sağlık vb.) | %1 (temel gıda, kitap, eğitim)
B4: Kurumlar vergisi | C4: Genel %25 | Bankalar/finansal kuruluşlar %30 | Halka açık şirketler (BIST'te min %20 fiili dolaşım) %23
B5: Yurt içi asgari kurumlar vergisi | C5: 7524 SK ile matrahın %10'undan az olamaz. Yeni kurulanlar ilk 3 yıl muaf.
B6: Geçici vergi | C6: Üçer aylık dönemler için %25; yıl sonunda kurumlar vergisinden mahsup edilir.
B7: Temettü stopajı | C7: 2025 sonu itibarıyla %15 (önceden %10 idi). Cumhurbaşkanı kararıyla değişebilir.
B8: Gelir vergisi (ücret) – 2026 tahmini dilimler | C8: <200.000 ₺: %15 | 200-420 bin: %20 | 420 bin-1,5 M: %27 | 1,5-5,5 M: %35 | >5,5 M: %40 (resmî dilimler açıklandığında güncelleyin)
B9: Damga vergisi (ücret) | C9: Binde 7,59 — brüt maaş üzerinden.
B10: SGK işçi | C10: %14 (emeklilik+sağlık) + %1 işsizlik = %15
B11: SGK işveren | C11: %20,5 normal; 5510 SK 5 puan indirimiyle %15,5 + %2 işsizlik = %17,5 (indirimli)
B12: Kira stopajı | C12: İşyeri kirası gerçek kişiden ise %20 (GVK 94/5). Tüzel kişiden kiralanıyorsa stopaj yok.
B13: Serbest meslek stopajı | C13: Genel %20 (SMMM, avukat, doktor vb. ödemelerde).
B14: KDV mükellefiyeti | C14: Limited şirket otomatik KDV mükellefidir; basit usul / muafiyet uygulanmaz.
... B20: Yasal Uyarı | C20: Bu tablo bilgilendirme amaçlıdır; nihai vergi yükümlülüğü için Mali Müşavir / YMM ile teyit ediniz. 2026 yılı resmi oranları yıl başında Gelir İdaresi Başkanlığı tarafından yayımlanır.
